odoo/addons/lot_ref_search/README.rst
odoo/addons/lot_ref_search/__init__.py
odoo/addons/lot_ref_search/__manifest__.py
odoo/addons/lot_ref_search/models/__init__.py
odoo/addons/lot_ref_search/models/stock_lot.py
odoo/addons/lot_ref_search/readme/CONTRIBUTORS.md
odoo/addons/lot_ref_search/readme/DESCRIPTION.md
odoo/addons/lot_ref_search/readme/USAGE.md
odoo/addons/lot_ref_search/static/description/icon.png
odoo/addons/lot_ref_search/static/description/index.html
odoo_addon_lot_ref_search-17.0.1.0.0.1.dist-info/METADATA
odoo_addon_lot_ref_search-17.0.1.0.0.1.dist-info/WHEEL
odoo_addon_lot_ref_search-17.0.1.0.0.1.dist-info/top_level.txt
odoo_addon_lot_ref_search-17.0.1.0.0.1.dist-info/RECORD
